README.md
setup.py
enlog/__init__.py
enlog/simple.py
enlog/utils.py
enlog.egg-info/PKG-INFO
enlog.egg-info/SOURCES.txt
enlog.egg-info/dependency_links.txt
enlog.egg-info/top_level.txt